xprompt_common/__init__.py
xprompt_common/api_schema/__init__.py
xprompt_common/api_schema/generate_schema.py
xprompt_common/base_service.py
xprompt_common/data_utils.py
xprompt_common/errors.py
xprompt_common/prompt_parser.py
xprompt_common-0.1.5.dist-info/METADATA
xprompt_common-0.1.5.dist-info/WHEEL
xprompt_common-0.1.5.dist-info/RECORD
