Metadata-Version: 2.1
Name: xprompt-common
Version: 0.1.5
Summary: 
Author: Yi Lu
Author-email: yilu331@gmail.com
Requires-Python: >=3.10,<4.0
Classifier: Programming Language :: Python :: 3
Classifier: Programming Language :: Python :: 3.10
Classifier: Programming Language :: Python :: 3.11
Requires-Dist: beautifulsoup4 (==4.12.2)
Requires-Dist: pydantic (==1.10.12)
Requires-Dist: pydantic-core (==2.6.3)
